speechline/__init__.py
speechline/config.py
speechline/run.py
speechline/aligners/__init__.py
speechline/aligners/punctuation_forced_aligner.py
speechline/classifiers/__init__.py
speechline/classifiers/wav2vec2.py
speechline/metrics/__init__.py
speechline/metrics/phoneme_error_rate.py
speechline/modules/__init__.py
speechline/modules/audio_classifier.py
speechline/modules/audio_module.py
speechline/modules/audio_transcriber.py
speechline/pipelines/__init__.py
speechline/pipelines/audio_classification.py
speechline/segmenters/__init__.py
speechline/segmenters/segmenter.py
speechline/segmenters/silence_segmenter.py
speechline/segmenters/word_overlap_segmenter.py
speechline/transcribers/__init__.py
speechline/transcribers/wav2vec2.py
speechline/transcribers/whisper.py
speechline/utils/__init__.py
speechline/utils/airtable.py
speechline/utils/dataset.py
speechline/utils/g2p.py
speechline/utils/io.py
speechline/utils/logger.py
speechline/utils/s3.py
speechline/utils/tokenizer.py
tests/__init__.py
tests/conftest.py
tests/test_data_logger.py
tests/test_g2p.py
tests/test_ml.py
tests/test_per.py
tests/test_pfa.py
tests/test_s3.py
tests/test_segmenters.py
tests/test_tokenizer.py
speechline-0.0.2.dist-info/LICENSE
speechline-0.0.2.dist-info/METADATA
speechline-0.0.2.dist-info/WHEEL
speechline-0.0.2.dist-info/top_level.txt
speechline-0.0.2.dist-info/RECORD
