Metadata-Version: 2.1
Name: speechline
Version: 0.0.2
Summary: An end-to-end, offline, batch audio categorization, transcription, and segmentation.
Home-page: https://github.com/bookbot-kids/speech-pipeline-v2
Author: w11wo
Author-email: w11wo <wilson@bookbotkids.com>, anantoj <gg.ananto@gmail.com>, DavidSamuell <davidsamuel.7878@gmail.com>
License: Apache License
Project-URL: Homepage, https://github.com/bookbot-kids/speechline
Project-URL: Bug Tracker, https://github.com/bookbot-kids/speechline/issues
Project-URL: Documentation, https://bookbot-kids.github.io/speechline/
Keywords: speech,audio,labeling,pipeline
Platform: linux
Platform: unix
Platform: windows
Classifier: License :: OSI Approved :: Apache Software License
Classifier: Programming Language :: Python :: 3
Requires-Python: >=3.7
License-File: LICENSE
Requires-Dist: torch
Requires-Dist: torchaudio
Requires-Dist: transformers
Requires-Dist: datasets[audio]
Requires-Dist: librosa
Requires-Dist: pandas
Requires-Dist: tqdm (==4.64.1)
Requires-Dist: p-tqdm (==1.4.0)
Requires-Dist: boto3 (==1.18.37)
Requires-Dist: botocore (==1.21.37)
Requires-Dist: pydub (==0.25.1)
Requires-Dist: requests
Requires-Dist: babygruut
Requires-Dist: levenshtein
Requires-Dist: nltk
Requires-Dist: g2p-id-py
